pyriksprot/__init__.py
pyriksprot/configuration/__init__.py
pyriksprot/configuration/config.py
pyriksprot/configuration/inject.py
pyriksprot/corpus/__init__.py
pyriksprot/corpus/corpus_index.py
pyriksprot/corpus/iterate.py
pyriksprot/corpus/parlaclarin/__init__.py
pyriksprot/corpus/parlaclarin/convert.py
pyriksprot/corpus/parlaclarin/iterate.py
pyriksprot/corpus/parlaclarin/parse.py
pyriksprot/corpus/parlaclarin/resources/__init__.py
pyriksprot/corpus/parlaclarin/resources/templates/__init__.py
pyriksprot/corpus/parlaclarin/resources/templates/paragraphs.txt.jinja
pyriksprot/corpus/parlaclarin/resources/templates/paragraphs.xml.jinja
pyriksprot/corpus/parlaclarin/resources/templates/speeches.cdata.xml.jinja
pyriksprot/corpus/parlaclarin/resources/templates/speeches.txt.jinja
pyriksprot/corpus/parlaclarin/resources/templates/speeches.xml.jinja
pyriksprot/corpus/parlaclarin/resources/xslt/parla_clarin_to_csv.xslt
pyriksprot/corpus/parlaclarin/resources/xslt/parla_clarin_to_xml.xslt
pyriksprot/corpus/parlaclarin/resources/xslt/test.xslt
pyriksprot/corpus/parlaclarin/tf.py
pyriksprot/corpus/tagged/__init__.py
pyriksprot/corpus/tagged/iterate.py
pyriksprot/corpus/tagged/persist.py
pyriksprot/corpus/utility.py
pyriksprot/dehyphenation/__init__.py
pyriksprot/dehyphenation/flair_dehyphen.py
pyriksprot/dehyphenation/swe_dehyphen.py
pyriksprot/dehyphenation/utility.py
pyriksprot/dispatch/__init__.py
pyriksprot/dispatch/dispatch.py
pyriksprot/dispatch/item.py
pyriksprot/dispatch/merge.py
pyriksprot/dispatch/utility.py
pyriksprot/foss/README.md
pyriksprot/foss/__init__.py
pyriksprot/foss/pos_tags.py
pyriksprot/foss/resources/bettertokenizer.sv
pyriksprot/foss/resources/bettertokenizer.sv.saldo-tokens
pyriksprot/foss/resources/punkt-nltk-svenska.pickle
pyriksprot/foss/sparv_tokenize.py
pyriksprot/foss/stopwords.py
pyriksprot/foss/untangle.py
pyriksprot/gitchen.py
pyriksprot/interface.py
pyriksprot/metadata/__init__.py
pyriksprot/metadata/codecs.py
pyriksprot-2024.10.3.dist-info/LICENSE
pyriksprot-2024.10.3.dist-info/METADATA
pyriksprot-2024.10.3.dist-info/WHEEL
pyriksprot-2024.10.3.dist-info/entry_points.txt
pyriksprot-2024.10.3.dist-info/RECORD
