Metadata-Version: 2.1
Name: pyriksprot
Version: 2024.10.3
Summary: Python API for Riksdagens Protokoll
Home-page: https://westac.se
License: Apache-2.0
Author: Roger Mähler
Author-email: roger.mahler@hotmail.com
Requires-Python: ==3.11.*
Classifier: License :: OSI Approved :: Apache Software License
Classifier: Operating System :: OS Independent
Classifier: Programming Language :: Python
Classifier: Programming Language :: Python :: 3
Classifier: Programming Language :: Python :: 3.11
Classifier: Topic :: Software Development
Requires-Dist: Jinja2
Requires-Dist: click
Requires-Dist: dynaconf (>=3.1.12,<4.0.0)
Requires-Dist: loguru
Requires-Dist: lz4
Requires-Dist: more-itertools
Requires-Dist: nltk (>=3.8.1,<4.0.0)
Requires-Dist: pandas
Requires-Dist: pathvalidate (>=2.5.2,<3.0.0)
Requires-Dist: pdoc
Requires-Dist: psycopg2-binary (>=2.9.5,<3.0.0)
Requires-Dist: pyarrow
Requires-Dist: pygit2 (>=1.11.1,<2.0.0)
Requires-Dist: python-dotenv
Requires-Dist: requests
Requires-Dist: sqlalchemy (>=2.0.6,<3.0.0)
Requires-Dist: tqdm
Requires-Dist: unidecode (>=1.3.6,<2.0.0)
Project-URL: Repository, https://github.com/welfare-state-analytics/pyriksprot
